helloworld.py
django_gcd-0.0.1.dist-info/LICENSE
django_gcd-0.0.1.dist-info/METADATA
django_gcd-0.0.1.dist-info/WHEEL
django_gcd-0.0.1.dist-info/top_level.txt
django_gcd-0.0.1.dist-info/RECORD
